git_remote_hg-1.0.5.data/scripts/git-hg-helper
git_remote_hg-1.0.5.data/scripts/git-remote-hg
git_remote_hg-1.0.5.dist-info/licenses/LICENSE
p3/bin/activate_this.py
git_remote_hg-1.0.5.dist-info/METADATA
git_remote_hg-1.0.5.dist-info/WHEEL
git_remote_hg-1.0.5.dist-info/top_level.txt
git_remote_hg-1.0.5.dist-info/RECORD
