Metadata-Version: 2.4
Name: git-remote-hg
Version: 1.0.5
Summary: access hg repositories as git remotes
Home-page: http://github.com/mnauw/git-remote-hg
Author: Mark Nauwelaerts
Author-email: mnauw@users.sourceforge.net
License: GPLv2
Keywords: git hg mercurial
Classifier: Programming Language :: Python
Classifier: Programming Language :: Python :: 2
Classifier: Programming Language :: Python :: 2.7
Classifier: Programming Language :: Python :: 3
Classifier: Programming Language :: Python :: 3.6
Classifier: License :: OSI Approved
Classifier: License :: OSI Approved :: GNU General Public License v2 (GPLv2)
Classifier: Development Status :: 5 - Production/Stable
Classifier: Intended Audience :: Developers
License-File: LICENSE
Dynamic: author
Dynamic: author-email
Dynamic: classifier
Dynamic: description
Dynamic: home-page
Dynamic: keywords
Dynamic: license
Dynamic: license-file
Dynamic: summary
